py_invoices/__init__.py
py_invoices/api/__init__.py
py_invoices/api/deps.py
py_invoices/api/main.py
py_invoices/api/routers/__init__.py
py_invoices/api/routers/audit.py
py_invoices/api/routers/clients.py
py_invoices/api/routers/companies.py
py_invoices/api/routers/credit_notes.py
py_invoices/api/routers/invoices.py
py_invoices/api/routers/payment_notes.py
py_invoices/api/routers/payments.py
py_invoices/api/routers/products.py
py_invoices/api/routers/validation.py
py_invoices/api/static/app.js
py_invoices/api/static/index.html
py_invoices/api/static/styles.css
py_invoices/backends/__init__.py
py_invoices/backends/files/__init__.py
py_invoices/backends/files/audit_repo.py
py_invoices/backends/files/client_repo.py
py_invoices/backends/files/company_repo.py
py_invoices/backends/files/invoice_repo.py
py_invoices/backends/files/payment_note_repo.py
py_invoices/backends/files/payment_repo.py
py_invoices/backends/files/plugin.py
py_invoices/backends/files/product_repo.py
py_invoices/backends/files/storage.py
py_invoices/backends/memory/__init__.py
py_invoices/backends/memory/audit_repo.py
py_invoices/backends/memory/client_repo.py
py_invoices/backends/memory/company_repo.py
py_invoices/backends/memory/invoice_repo.py
py_invoices/backends/memory/payment_note_repo.py
py_invoices/backends/memory/payment_repo.py
py_invoices/backends/memory/plugin.py
py_invoices/backends/memory/product_repo.py
py_invoices/backends/mysql/plugin.py
py_invoices/backends/postgres/plugin.py
py_invoices/backends/sqlite/__init__.py
py_invoices/backends/sqlite/plugin.py
py_invoices/backends/sqlmodel/__init__.py
py_invoices/backends/sqlmodel/audit_repo.py
py_invoices/backends/sqlmodel/base_plugin.py
py_invoices/backends/sqlmodel/client_repo.py
py_invoices/backends/sqlmodel/company_repo.py
py_invoices/backends/sqlmodel/invoice_repo.py
py_invoices/backends/sqlmodel/models.py
py_invoices/backends/sqlmodel/payment_note_repo.py
py_invoices/backends/sqlmodel/payment_repo.py
py_invoices-1.8.2.dist-info/METADATA
py_invoices-1.8.2.dist-info/WHEEL
py_invoices-1.8.2.dist-info/entry_points.txt
py_invoices-1.8.2.dist-info/licenses/LICENSE
py_invoices-1.8.2.dist-info/RECORD
