Metadata-Version: 2.4
Name: py-invoices
Version: 1.8.2
Summary: Framework-agnostic invoice management with pluggable storage backends
Project-URL: Homepage, https://github.com/romamo/py-invoices
Author-email: Roman Medvedev <pypi@romavm.dev>
License: MIT
License-File: LICENSE
Requires-Python: >=3.10
Requires-Dist: jinja2>=3.1.5
Requires-Dist: pydantic-invoices>=1.2.2
Requires-Dist: pydantic-settings>=2.0.0
Requires-Dist: pydantic>=2.0.0
Requires-Dist: python-multipart>=0.0.21
Provides-Extra: all
Requires-Dist: fastapi>=0.100.0; extra == 'all'
Requires-Dist: psycopg2-binary>=2.9.0; extra == 'all'
Requires-Dist: pymysql>=1.1.0; extra == 'all'
Requires-Dist: python-dotenv>=1.0.0; extra == 'all'
Requires-Dist: pyyaml>=6.0; extra == 'all'
Requires-Dist: rich>=14.2.0; extra == 'all'
Requires-Dist: sqlmodel>=0.0.22; extra == 'all'
Requires-Dist: typer>=0.9.0; extra == 'all'
Requires-Dist: uvicorn>=0.20.0; extra == 'all'
Requires-Dist: weasyprint>=63.1; extra == 'all'
Provides-Extra: api
Requires-Dist: fastapi>=0.100.0; extra == 'api'
Requires-Dist: uvicorn>=0.20.0; extra == 'api'
Provides-Extra: cli
Requires-Dist: rich>=14.2.0; extra == 'cli'
Requires-Dist: typer>=0.9.0; extra == 'cli'
Provides-Extra: dotenv
Requires-Dist: python-dotenv>=1.0.0; extra == 'dotenv'
Provides-Extra: files
Provides-Extra: memory
Provides-Extra: mysql
Requires-Dist: pymysql>=1.1.0; extra == 'mysql'
Requires-Dist: sqlmodel>=0.0.22; extra == 'mysql'
Provides-Extra: pdf
Requires-Dist: pyyaml>=6.0; extra == 'pdf'
Requires-Dist: weasyprint>=63.1; extra == 'pdf'
Provides-Extra: postgres
Requires-Dist: psycopg2-binary>=2.9.0; extra == 'postgres'
Requires-Dist: sqlmodel>=0.0.22; extra == 'postgres'
Provides-Extra: sqlite
Requires-Dist: sqlmodel>=0.0.22; extra == 'sqlite'
Provides-Extra: yaml
Requires-Dist: pyyaml>=6.0; extra == 'yaml'
